Tool.py
cxrtestlib/__init__.py
cxrtestlib/cxrlibone.py
cxrtestlib-1.2.0.dist-info/LICENSE.txt
cxrtestlib-1.2.0.dist-info/METADATA
cxrtestlib-1.2.0.dist-info/WHEEL
cxrtestlib-1.2.0.dist-info/top_level.txt
cxrtestlib-1.2.0.dist-info/RECORD
