Metadata-Version: 2.1
Name: cxrtestlib
Version: 1.2.0
Summary: thie is nb lib
Home-page: UNKNOWN
Author: Cxr
Author-email: 1318304701@qq.com
License: MIT
Platform: UNKNOWN
License-File: LICENSE.txt
